{
  "articleFeedback": {
    "question": "Did this article help solve your problem?",
    "thanksMsg": "Thanks for submitting your feedback!"
  },
  "error": {
    "defaultTitle": "",
    "title": "Whoops!"
  },
  "login": "Log in",
  "logout": "Log out",
  "search": {
    "shortplaceholder": "",
    "placeholder": "Search our help centre..."
  },
  "pageTitles": {
    "error": "",
    "error404": "",
    "article": "{{article.title}}",
    "category": "{{category.title}}",
    "error401": "",
    "home": "",
    "search": ""
  },
  "notification": {
    "loggedIn": "Logged in.",
    "loggedOut": "Logged out.",
    "generalError": "Sorry something went wrong, please try again. \n({{notificationKey}})",
    "loginError": "Sorry, please try again. {{notificationKey}} (error code {{errorCode}})"
  },
  "required": "Required",
  "invalid_email": "Invalid email"
}
